psython/__init__.py
psython-0.0.16.dist-info/LICENSE
psython-0.0.16.dist-info/METADATA
psython-0.0.16.dist-info/WHEEL
psython-0.0.16.dist-info/top_level.txt
psython-0.0.16.dist-info/RECORD
