Metadata-Version: 2.1
Name: psython
Version: 0.0.16
Summary: A package for SPSS methods
Home-page: https://github.com/cxt9/psython
Author: Doron Goldberg
Author-email: doron.goldberg@gmail.com
License: UNKNOWN
Platform: UNKNOWN
Classifier: Programming Language :: Python :: 3
Classifier: License :: OSI Approved :: MIT License
Classifier: Operating System :: OS Independent
Requires-Python: >=3.6
